[
    {
        "projects": {
            "code": "synthetic_dataset_1"
        },
        "submitter_id": "acknowledgement_fd27ebeee3",
        "type": "acknowledgement"
    },
    {
        "projects": {
            "code": "synthetic_dataset_1"
        },
        "submitter_id": "acknowledgement_7fd4dbc803",
        "type": "acknowledgement"
    },
    {
        "projects": {
            "code": "synthetic_dataset_1"
        },
        "submitter_id": "acknowledgement_47309a5803",
        "type": "acknowledgement"
    },
    {
        "projects": {
            "code": "synthetic_dataset_1"
        },
        "submitter_id": "acknowledgement_b244116214",
        "type": "acknowledgement"
    },
    {
        "projects": {
            "code": "synthetic_dataset_1"
        },
        "submitter_id": "acknowledgement_aa198bda70",
        "type": "acknowledgement"
    },
    {
        "projects": {
            "code": "synthetic_dataset_1"
        },
        "submitter_id": "acknowledgement_3b061acd47",
        "type": "acknowledgement"
    },
    {
        "projects": {
            "code": "synthetic_dataset_1"
        },
        "submitter_id": "acknowledgement_ebb10833e4",
        "type": "acknowledgement"
    },
    {
        "projects": {
            "code": "synthetic_dataset_1"
        },
        "submitter_id": "acknowledgement_666642b50d",
        "type": "acknowledgement"
    },
    {
        "projects": {
            "code": "synthetic_dataset_1"
        },
        "submitter_id": "acknowledgement_b085949d14",
        "type": "acknowledgement"
    },
    {
        "projects": {
            "code": "synthetic_dataset_1"
        },
        "submitter_id": "acknowledgement_fd3582670e",
        "type": "acknowledgement"
    },
    {
        "projects": {
            "code": "synthetic_dataset_1"
        },
        "submitter_id": "acknowledgement_2674346e4c",
        "type": "acknowledgement"
    },
    {
        "projects": {
            "code": "synthetic_dataset_1"
        },
        "submitter_id": "acknowledgement_ef5cd9dd2b",
        "type": "acknowledgement"
    },
    {
        "projects": {
            "code": "synthetic_dataset_1"
        },
        "submitter_id": "acknowledgement_ba83a5f666",
        "type": "acknowledgement"
    },
    {
        "projects": {
            "code": "synthetic_dataset_1"
        },
        "submitter_id": "acknowledgement_f280bfcee6",
        "type": "acknowledgement"
    },
    {
        "projects": {
            "code": "synthetic_dataset_1"
        },
        "submitter_id": "acknowledgement_114d03a613",
        "type": "acknowledgement"
    },
    {
        "projects": {
            "code": "synthetic_dataset_1"
        },
        "submitter_id": "acknowledgement_b16ca68561",
        "type": "acknowledgement"
    },
    {
        "projects": {
            "code": "synthetic_dataset_1"
        },
        "submitter_id": "acknowledgement_15ba81f3af",
        "type": "acknowledgement"
    },
    {
        "projects": {
            "code": "synthetic_dataset_1"
        },
        "submitter_id": "acknowledgement_81df61f83c",
        "type": "acknowledgement"
    },
    {
        "projects": {
            "code": "synthetic_dataset_1"
        },
        "submitter_id": "acknowledgement_ba54127a98",
        "type": "acknowledgement"
    },
    {
        "projects": {
            "code": "synthetic_dataset_1"
        },
        "submitter_id": "acknowledgement_332d54db25",
        "type": "acknowledgement"
    },
    {
        "projects": {
            "code": "synthetic_dataset_1"
        },
        "submitter_id": "acknowledgement_359d6f8219",
        "type": "acknowledgement"
    },
    {
        "projects": {
            "code": "synthetic_dataset_1"
        },
        "submitter_id": "acknowledgement_b1380bf91a",
        "type": "acknowledgement"
    },
    {
        "projects": {
            "code": "synthetic_dataset_1"
        },
        "submitter_id": "acknowledgement_582919694e",
        "type": "acknowledgement"
    },
    {
        "projects": {
            "code": "synthetic_dataset_1"
        },
        "submitter_id": "acknowledgement_be251ceb88",
        "type": "acknowledgement"
    },
    {
        "projects": {
            "code": "synthetic_dataset_1"
        },
        "submitter_id": "acknowledgement_1a20d6d9bf",
        "type": "acknowledgement"
    },
    {
        "projects": {
            "code": "synthetic_dataset_1"
        },
        "submitter_id": "acknowledgement_f337f7b28a",
        "type": "acknowledgement"
    },
    {
        "projects": {
            "code": "synthetic_dataset_1"
        },
        "submitter_id": "acknowledgement_11f103c1d9",
        "type": "acknowledgement"
    },
    {
        "projects": {
            "code": "synthetic_dataset_1"
        },
        "submitter_id": "acknowledgement_86bb8da1c5",
        "type": "acknowledgement"
    },
    {
        "projects": {
            "code": "synthetic_dataset_1"
        },
        "submitter_id": "acknowledgement_85972a1716",
        "type": "acknowledgement"
    },
    {
        "projects": {
            "code": "synthetic_dataset_1"
        },
        "submitter_id": "acknowledgement_e4a9f11426",
        "type": "acknowledgement"
    },
    {
        "projects": {
            "code": "synthetic_dataset_1"
        },
        "submitter_id": "acknowledgement_4d4d6bb68c",
        "type": "acknowledgement"
    },
    {
        "projects": {
            "code": "synthetic_dataset_1"
        },
        "submitter_id": "acknowledgement_caf08626df",
        "type": "acknowledgement"
    },
    {
        "projects": {
            "code": "synthetic_dataset_1"
        },
        "submitter_id": "acknowledgement_f676f1aa39",
        "type": "acknowledgement"
    },
    {
        "projects": {
            "code": "synthetic_dataset_1"
        },
        "submitter_id": "acknowledgement_d88a06a8d1",
        "type": "acknowledgement"
    },
    {
        "projects": {
            "code": "synthetic_dataset_1"
        },
        "submitter_id": "acknowledgement_9f33b9fa5e",
        "type": "acknowledgement"
    },
    {
        "projects": {
            "code": "synthetic_dataset_1"
        },
        "submitter_id": "acknowledgement_2bfb1e4d6d",
        "type": "acknowledgement"
    },
    {
        "projects": {
            "code": "synthetic_dataset_1"
        },
        "submitter_id": "acknowledgement_5b30188d63",
        "type": "acknowledgement"
    },
    {
        "projects": {
            "code": "synthetic_dataset_1"
        },
        "submitter_id": "acknowledgement_a5a02c3f02",
        "type": "acknowledgement"
    },
    {
        "projects": {
            "code": "synthetic_dataset_1"
        },
        "submitter_id": "acknowledgement_12e7747190",
        "type": "acknowledgement"
    },
    {
        "projects": {
            "code": "synthetic_dataset_1"
        },
        "submitter_id": "acknowledgement_390cbee6b7",
        "type": "acknowledgement"
    },
    {
        "projects": {
            "code": "synthetic_dataset_1"
        },
        "submitter_id": "acknowledgement_3acfa2fd6e",
        "type": "acknowledgement"
    },
    {
        "projects": {
            "code": "synthetic_dataset_1"
        },
        "submitter_id": "acknowledgement_6a171f3f82",
        "type": "acknowledgement"
    },
    {
        "projects": {
            "code": "synthetic_dataset_1"
        },
        "submitter_id": "acknowledgement_7c72d33d6d",
        "type": "acknowledgement"
    },
    {
        "projects": {
            "code": "synthetic_dataset_1"
        },
        "submitter_id": "acknowledgement_624cac22f4",
        "type": "acknowledgement"
    },
    {
        "projects": {
            "code": "synthetic_dataset_1"
        },
        "submitter_id": "acknowledgement_70af25d5f7",
        "type": "acknowledgement"
    },
    {
        "projects": {
            "code": "synthetic_dataset_1"
        },
        "submitter_id": "acknowledgement_d01390aada",
        "type": "acknowledgement"
    },
    {
        "projects": {
            "code": "synthetic_dataset_1"
        },
        "submitter_id": "acknowledgement_aada0cde32",
        "type": "acknowledgement"
    },
    {
        "projects": {
            "code": "synthetic_dataset_1"
        },
        "submitter_id": "acknowledgement_8cfd121547",
        "type": "acknowledgement"
    },
    {
        "projects": {
            "code": "synthetic_dataset_1"
        },
        "submitter_id": "acknowledgement_7283c55643",
        "type": "acknowledgement"
    },
    {
        "projects": {
            "code": "synthetic_dataset_1"
        },
        "submitter_id": "acknowledgement_234e9b5aea",
        "type": "acknowledgement"
    },
    {
        "projects": {
            "code": "synthetic_dataset_1"
        },
        "submitter_id": "acknowledgement_a02eb0089f",
        "type": "acknowledgement"
    },
    {
        "projects": {
            "code": "synthetic_dataset_1"
        },
        "submitter_id": "acknowledgement_534e15002c",
        "type": "acknowledgement"
    },
    {
        "projects": {
            "code": "synthetic_dataset_1"
        },
        "submitter_id": "acknowledgement_2d50f24797",
        "type": "acknowledgement"
    },
    {
        "projects": {
            "code": "synthetic_dataset_1"
        },
        "submitter_id": "acknowledgement_1d050b539a",
        "type": "acknowledgement"
    },
    {
        "projects": {
            "code": "synthetic_dataset_1"
        },
        "submitter_id": "acknowledgement_258dcc8923",
        "type": "acknowledgement"
    },
    {
        "projects": {
            "code": "synthetic_dataset_1"
        },
        "submitter_id": "acknowledgement_8ada588f3f",
        "type": "acknowledgement"
    },
    {
        "projects": {
            "code": "synthetic_dataset_1"
        },
        "submitter_id": "acknowledgement_2220634086",
        "type": "acknowledgement"
    },
    {
        "projects": {
            "code": "synthetic_dataset_1"
        },
        "submitter_id": "acknowledgement_90ab40da60",
        "type": "acknowledgement"
    },
    {
        "projects": {
            "code": "synthetic_dataset_1"
        },
        "submitter_id": "acknowledgement_da8e595f4e",
        "type": "acknowledgement"
    },
    {
        "projects": {
            "code": "synthetic_dataset_1"
        },
        "submitter_id": "acknowledgement_ddd0bc44eb",
        "type": "acknowledgement"
    },
    {
        "projects": {
            "code": "synthetic_dataset_1"
        },
        "submitter_id": "acknowledgement_f7b85295af",
        "type": "acknowledgement"
    },
    {
        "projects": {
            "code": "synthetic_dataset_1"
        },
        "submitter_id": "acknowledgement_bddbd93796",
        "type": "acknowledgement"
    },
    {
        "projects": {
            "code": "synthetic_dataset_1"
        },
        "submitter_id": "acknowledgement_a8fab967be",
        "type": "acknowledgement"
    },
    {
        "projects": {
            "code": "synthetic_dataset_1"
        },
        "submitter_id": "acknowledgement_e11f83ba33",
        "type": "acknowledgement"
    },
    {
        "projects": {
            "code": "synthetic_dataset_1"
        },
        "submitter_id": "acknowledgement_d33dd67b5a",
        "type": "acknowledgement"
    },
    {
        "projects": {
            "code": "synthetic_dataset_1"
        },
        "submitter_id": "acknowledgement_c146a12274",
        "type": "acknowledgement"
    },
    {
        "projects": {
            "code": "synthetic_dataset_1"
        },
        "submitter_id": "acknowledgement_dbf74be6c5",
        "type": "acknowledgement"
    },
    {
        "projects": {
            "code": "synthetic_dataset_1"
        },
        "submitter_id": "acknowledgement_a4a57bfbfe",
        "type": "acknowledgement"
    },
    {
        "projects": {
            "code": "synthetic_dataset_1"
        },
        "submitter_id": "acknowledgement_b383dcc83b",
        "type": "acknowledgement"
    },
    {
        "projects": {
            "code": "synthetic_dataset_1"
        },
        "submitter_id": "acknowledgement_5ec24a9768",
        "type": "acknowledgement"
    },
    {
        "projects": {
            "code": "synthetic_dataset_1"
        },
        "submitter_id": "acknowledgement_7177758645",
        "type": "acknowledgement"
    },
    {
        "projects": {
            "code": "synthetic_dataset_1"
        },
        "submitter_id": "acknowledgement_d6cc9567b3",
        "type": "acknowledgement"
    },
    {
        "projects": {
            "code": "synthetic_dataset_1"
        },
        "submitter_id": "acknowledgement_a48a5d7f38",
        "type": "acknowledgement"
    },
    {
        "projects": {
            "code": "synthetic_dataset_1"
        },
        "submitter_id": "acknowledgement_f76cf69f71",
        "type": "acknowledgement"
    },
    {
        "projects": {
            "code": "synthetic_dataset_1"
        },
        "submitter_id": "acknowledgement_dded41a4ec",
        "type": "acknowledgement"
    },
    {
        "projects": {
            "code": "synthetic_dataset_1"
        },
        "submitter_id": "acknowledgement_80cdd84044",
        "type": "acknowledgement"
    },
    {
        "projects": {
            "code": "synthetic_dataset_1"
        },
        "submitter_id": "acknowledgement_f554775eb6",
        "type": "acknowledgement"
    },
    {
        "projects": {
            "code": "synthetic_dataset_1"
        },
        "submitter_id": "acknowledgement_57033d3efe",
        "type": "acknowledgement"
    },
    {
        "projects": {
            "code": "synthetic_dataset_1"
        },
        "submitter_id": "acknowledgement_ade9a0c19f",
        "type": "acknowledgement"
    },
    {
        "projects": {
            "code": "synthetic_dataset_1"
        },
        "submitter_id": "acknowledgement_0244e797b7",
        "type": "acknowledgement"
    },
    {
        "projects": {
            "code": "synthetic_dataset_1"
        },
        "submitter_id": "acknowledgement_7ad98573a3",
        "type": "acknowledgement"
    },
    {
        "projects": {
            "code": "synthetic_dataset_1"
        },
        "submitter_id": "acknowledgement_a3943bfcb1",
        "type": "acknowledgement"
    },
    {
        "projects": {
            "code": "synthetic_dataset_1"
        },
        "submitter_id": "acknowledgement_28c81a5721",
        "type": "acknowledgement"
    },
    {
        "projects": {
            "code": "synthetic_dataset_1"
        },
        "submitter_id": "acknowledgement_f924e276d1",
        "type": "acknowledgement"
    },
    {
        "projects": {
            "code": "synthetic_dataset_1"
        },
        "submitter_id": "acknowledgement_01b8c0bdcd",
        "type": "acknowledgement"
    },
    {
        "projects": {
            "code": "synthetic_dataset_1"
        },
        "submitter_id": "acknowledgement_4ec3cd42de",
        "type": "acknowledgement"
    },
    {
        "projects": {
            "code": "synthetic_dataset_1"
        },
        "submitter_id": "acknowledgement_5e7d61a043",
        "type": "acknowledgement"
    },
    {
        "projects": {
            "code": "synthetic_dataset_1"
        },
        "submitter_id": "acknowledgement_c7a4b0e769",
        "type": "acknowledgement"
    },
    {
        "projects": {
            "code": "synthetic_dataset_1"
        },
        "submitter_id": "acknowledgement_c02104a5d8",
        "type": "acknowledgement"
    },
    {
        "projects": {
            "code": "synthetic_dataset_1"
        },
        "submitter_id": "acknowledgement_41cb2176b5",
        "type": "acknowledgement"
    },
    {
        "projects": {
            "code": "synthetic_dataset_1"
        },
        "submitter_id": "acknowledgement_fee3c2275b",
        "type": "acknowledgement"
    },
    {
        "projects": {
            "code": "synthetic_dataset_1"
        },
        "submitter_id": "acknowledgement_64dd839445",
        "type": "acknowledgement"
    },
    {
        "projects": {
            "code": "synthetic_dataset_1"
        },
        "submitter_id": "acknowledgement_71750b940a",
        "type": "acknowledgement"
    },
    {
        "projects": {
            "code": "synthetic_dataset_1"
        },
        "submitter_id": "acknowledgement_96b8aca223",
        "type": "acknowledgement"
    },
    {
        "projects": {
            "code": "synthetic_dataset_1"
        },
        "submitter_id": "acknowledgement_7c762efa88",
        "type": "acknowledgement"
    },
    {
        "projects": {
            "code": "synthetic_dataset_1"
        },
        "submitter_id": "acknowledgement_75cf71a7dc",
        "type": "acknowledgement"
    },
    {
        "projects": {
            "code": "synthetic_dataset_1"
        },
        "submitter_id": "acknowledgement_82a6f67407",
        "type": "acknowledgement"
    },
    {
        "projects": {
            "code": "synthetic_dataset_1"
        },
        "submitter_id": "acknowledgement_4e97361f6a",
        "type": "acknowledgement"
    },
    {
        "projects": {
            "code": "synthetic_dataset_1"
        },
        "submitter_id": "acknowledgement_a8cb259ffa",
        "type": "acknowledgement"
    },
    {
        "projects": {
            "code": "synthetic_dataset_1"
        },
        "submitter_id": "acknowledgement_9cfcbd7b33",
        "type": "acknowledgement"
    },
    {
        "projects": {
            "code": "synthetic_dataset_1"
        },
        "submitter_id": "acknowledgement_47c068a37b",
        "type": "acknowledgement"
    },
    {
        "projects": {
            "code": "synthetic_dataset_1"
        },
        "submitter_id": "acknowledgement_5e2fe6ebbf",
        "type": "acknowledgement"
    },
    {
        "projects": {
            "code": "synthetic_dataset_1"
        },
        "submitter_id": "acknowledgement_a1df658ec8",
        "type": "acknowledgement"
    },
    {
        "projects": {
            "code": "synthetic_dataset_1"
        },
        "submitter_id": "acknowledgement_0ec72711c8",
        "type": "acknowledgement"
    },
    {
        "projects": {
            "code": "synthetic_dataset_1"
        },
        "submitter_id": "acknowledgement_f4d21c0627",
        "type": "acknowledgement"
    },
    {
        "projects": {
            "code": "synthetic_dataset_1"
        },
        "submitter_id": "acknowledgement_0e0704fb02",
        "type": "acknowledgement"
    },
    {
        "projects": {
            "code": "synthetic_dataset_1"
        },
        "submitter_id": "acknowledgement_c78b797545",
        "type": "acknowledgement"
    },
    {
        "projects": {
            "code": "synthetic_dataset_1"
        },
        "submitter_id": "acknowledgement_8cda868fb5",
        "type": "acknowledgement"
    },
    {
        "projects": {
            "code": "synthetic_dataset_1"
        },
        "submitter_id": "acknowledgement_12f295483e",
        "type": "acknowledgement"
    },
    {
        "projects": {
            "code": "synthetic_dataset_1"
        },
        "submitter_id": "acknowledgement_b1f3ee6f59",
        "type": "acknowledgement"
    }
]